pymsbmnl/__init__.py
pymsbmnl/adapter.py
pymsbmnl/binIO.py
pymsbmnl/helper.py
pymsbmnl/msbf.py
pymsbmnl/msbt.py
pymsbmnl/py.typed
pymsbmnl-1.1.0.dist-info/LICENSE
pymsbmnl-1.1.0.dist-info/METADATA
pymsbmnl-1.1.0.dist-info/WHEEL
pymsbmnl-1.1.0.dist-info/RECORD
