Metadata-Version: 2.3
Name: pymsbmnl
Version: 1.1.0
Summary: Python library for Nintendo's MSBT & MSBF formats (Mario & Luigi Modding fork).
License: Apache-2.0
Keywords: nintendo,lms,msbt,msbf,modding
Author: Aurum
Requires-Python: >=3.10,<4.0
Classifier: License :: OSI Approved :: Apache Software License
Classifier: Programming Language :: Python :: 3
Classifier: Programming Language :: Python :: 3.10
Classifier: Programming Language :: Python :: 3.11
Classifier: Programming Language :: Python :: 3.12
Classifier: Programming Language :: Python :: 3.13
Project-URL: Repository, https://github.com/MnL-Modding/pymsbmnl
